odoo8_addon_mgmtsystem_survey-8.0.1.0.0.99.dev8-py2.7-nspkg.pth
odoo8_addon_mgmtsystem_survey-8.0.1.0.0.99.dev8.dist-info/DESCRIPTION.rst
odoo8_addon_mgmtsystem_survey-8.0.1.0.0.99.dev8.dist-info/METADATA
odoo8_addon_mgmtsystem_survey-8.0.1.0.0.99.dev8.dist-info/RECORD
odoo8_addon_mgmtsystem_survey-8.0.1.0.0.99.dev8.dist-info/WHEEL
odoo8_addon_mgmtsystem_survey-8.0.1.0.0.99.dev8.dist-info/metadata.json
odoo8_addon_mgmtsystem_survey-8.0.1.0.0.99.dev8.dist-info/namespace_packages.txt
odoo8_addon_mgmtsystem_survey-8.0.1.0.0.99.dev8.dist-info/top_level.txt
odoo_addons/mgmtsystem_survey/__init__.py
odoo_addons/mgmtsystem_survey/__openerp__.py
odoo_addons/mgmtsystem_survey/data/survey_stage.xml
odoo_addons/mgmtsystem_survey/i18n/de.po
odoo_addons/mgmtsystem_survey/i18n/es.po
odoo_addons/mgmtsystem_survey/i18n/fr.po
odoo_addons/mgmtsystem_survey/i18n/hr.po
odoo_addons/mgmtsystem_survey/i18n/id.po
odoo_addons/mgmtsystem_survey/i18n/mgmtsystem_survey.pot
odoo_addons/mgmtsystem_survey/i18n/nb.po
odoo_addons/mgmtsystem_survey/i18n/pt_BR.po
odoo_addons/mgmtsystem_survey/i18n/sl.po
odoo_addons/mgmtsystem_survey/i18n/sv.po
odoo_addons/mgmtsystem_survey/i18n/vi.po
odoo_addons/mgmtsystem_survey/static/description/icon.png
odoo_addons/mgmtsystem_survey/views/survey_survey.xml
